{
  "project_info": {
    "project_number": "820215092127",
    "project_id": "financemanager-fedb8",
    "storage_bucket": "financemanager-fedb8.appspot.com"
  },
  "client": [
    {
      "client_info": {
        "mobilesdk_app_id": "1:820215092127:android:9223b7a0e4dcd0481123aa",
        "android_client_info": {
          "package_name": "com.example.myapplication"
        }
      },
      "oauth_client": [],
      "api_key": [
        {
          "current_key": "AIzaSyBxbuniY11rXtvhPkznlAtupRQ20UbG4ks"
        }
      ],
      "services": {
        "appinvite_service": {
          "other_platform_oauth_client": []
        }
      }
    }
  ],
  "configuration_version": "1"
}